<?xml version="1.0" encoding="UTF-8"?>
<!DOCTYPE hibernate-mapping PUBLIC "-//Hibernate/Hibernate Mapping DTD 3.0//EN"
                                   "http://hibernate.sourceforge.net/hibernate-mapping-3.0.dtd">
<hibernate-mapping>
    <class name="pe.com.backus.scaudi.domain.CentroDistribucion" table="T_CENTRODIST">
        <id column="ID_CENTRO_DIST" name="idCentroDist" type="java.lang.Integer">
            <generator class="native"/>
        </id>
        <property length="50" name="descripcion" not-null="true" type="java.lang.String">
            <column name="VC_DESCRIPCION" sql-type="VARCHAR"/>
        </property>
        <many-to-one class="pe.com.backus.scaudi.domain.Region"
            name="region" not-null="true">
            <column name="IN_IDREGION"/>
        </many-to-one>
    </class>
</hibernate-mapping>
